bolt_agent_toolkit/__init__.py
bolt_agent_toolkit/api.py
bolt_agent_toolkit/configuration.py
bolt_agent_toolkit/products.py
bolt_agent_toolkit/prompts.py
bolt_agent_toolkit/py.typed
bolt_agent_toolkit/schema.py
bolt_agent_toolkit/tools.py
bolt_agent_toolkit/hooks/__init__.py
bolt_agent_toolkit/langchain/__init__.py
bolt_agent_toolkit/langchain/tool.py
bolt_agent_toolkit/langchain/toolkit.py
bolt_agent_toolkit/modelcontextprotocol/__init__.py
bolt_agent_toolkit/modelcontextprotocol/toolkit.py
bolt_agent_toolkit/modelcontextprotocol/tools/__init__.py
bolt_agent_toolkit/modelcontextprotocol/tools/subscription.py
bolt_agent_toolkit/openai/__init__.py
bolt_agent_toolkit/openai/hooks.py
bolt_agent_toolkit/openai/tool.py
bolt_agent_toolkit/openai/toolkit.py
bolt_agent_toolkit-0.1.1.dist-info/METADATA
bolt_agent_toolkit-0.1.1.dist-info/WHEEL
bolt_agent_toolkit-0.1.1.dist-info/licenses/LICENSE
bolt_agent_toolkit-0.1.1.dist-info/RECORD
