Metadata-Version: 2.4
Name: bolt-agent-toolkit
Version: 0.1.1
Summary: Bolt Agent Toolkit
Project-URL: Bug Tracker, https://github.com/BoltApp/agent-toolkit/issues
Project-URL: Source Code, https://github.com/BoltApp/agent-toolkit/python
Author-email: Bolt <support@bolt.com>
License-File: LICENSE
Keywords: bolt,mcp,modelcontextprotocol
Requires-Python: >=3.11
Requires-Dist: bolt-api-sdk==0.3.0
Requires-Dist: fastmcp>=2.10.2
Requires-Dist: langchain-community>=0.3.27
Requires-Dist: langchain-openai>=0.3.28
Requires-Dist: langchain>=0.3.26
Requires-Dist: langgraph>=0.5.3
Requires-Dist: openai-agents>=0.2.5
Requires-Dist: openai>=1.99.6
Requires-Dist: pydantic>=2.11.7
Requires-Dist: python-dotenv>=1.1.1
